local/__init__.py
local/__main__.py
local/local.py
local/util.py
local-1.0.0.dist-info/LICENSE
local-1.0.0.dist-info/METADATA
local-1.0.0.dist-info/WHEEL
local-1.0.0.dist-info/entry_points.txt
local-1.0.0.dist-info/top_level.txt
local-1.0.0.dist-info/RECORD
